{"data":{"athletes":{"first_name":"Shane","last_name":"Kiernan"},"allRaces":{"nodes":[{"fields":{"slug":"crazy_store_lighthouse_ten_night_race_2019-03-06_10_run"},"name":"Crazy Store Lighthouse Ten Night Race","distance":10,"date":"2019-03-06","results":[{"name":"john mawingo","time":"0:37:49","position":44,"category_position":null,"gender_position":null},{"name":"chris erlangsen","time":"0:42:06","position":112,"category_position":null,"gender_position":null},{"name":"jean minaar","time":"0:43:49","position":160,"category_position":null,"gender_position":null},{"name":"unathi solora","time":"0:44:20","position":178,"category_position":null,"gender_position":null},{"name":"kanakana mushangayi","time":"0:45:18","position":222,"category_position":null,"gender_position":null},{"name":"andrew erlangsen","time":"0:45:23","position":225,"category_position":null,"gender_position":null},{"name":"matthew weyer","time":"0:46:10","position":237,"category_position":null,"gender_position":null},{"name":"nancy will","time":"0:47:59","position":286,"category_position":null,"gender_position":null},{"name":"david isaacs","time":"0:49:17","position":343,"category_position":null,"gender_position":null},{"name":"christopher schnehage","time":"0:52:26","position":464,"category_position":null,"gender_position":null},{"name":"john dawes","time":"0:52:57","position":487,"category_position":null,"gender_position":null},{"name":"lily joan ithier","time":"0:53:49","position":532,"category_position":null,"gender_position":null},{"name":"mervin schnehage","time":"0:55:02","position":582,"category_position":null,"gender_position":null},{"name":"alison smith","time":"0:55:10","position":586,"category_position":null,"gender_position":null},{"name":"anwar omar","time":"0:56:48","position":659,"category_position":null,"gender_position":null},{"name":"shamiel mathews","time":"0:56:49","position":660,"category_position":null,"gender_position":null},{"name":"hylton christie-smith","time":"0:57:49","position":698,"category_position":null,"gender_position":null},{"name":"maitele tshifularo","time":"0:58:30","position":747,"category_position":null,"gender_position":null},{"name":" no card","time":"1:01:44","position":909,"category_position":null,"gender_position":null},{"name":"marlene james","time":"1:01:48","position":910,"category_position":null,"gender_position":null},{"name":"jo kannemeyer","time":"1:02:19","position":936,"category_position":null,"gender_position":null},{"name":"cameron clarke","time":"1:03:43","position":990,"category_position":null,"gender_position":null},{"name":"taryn christie-smith","time":"1:04:06","position":1022,"category_position":null,"gender_position":null},{"name":"gcinikaya dlodlo","time":"1:04:53","position":1046,"category_position":null,"gender_position":null},{"name":"chris mackrill","time":"1:06:32","position":1101,"category_position":null,"gender_position":null},{"name":"kaare james","time":"1:06:40","position":1107,"category_position":null,"gender_position":null},{"name":"calvin leen","time":"1:07:03","position":1126,"category_position":null,"gender_position":null},{"name":"clara machado","time":"1:07:17","position":1132,"category_position":null,"gender_position":null},{"name":"monique lentz","time":"1:09:11","position":1180,"category_position":null,"gender_position":null},{"name":"genevieve lentz","time":"1:10:02","position":1199,"category_position":null,"gender_position":null},{"name":"r toyer","time":"1:10:48","position":1212,"category_position":null,"gender_position":null},{"name":"tarryn clarke","time":"1:12:10","position":1252,"category_position":null,"gender_position":null},{"name":"lee-ann harris","time":"1:12:40","position":1265,"category_position":null,"gender_position":null},{"name":"susan purchase","time":"1:16:13","position":1334,"category_position":null,"gender_position":null},{"name":"meghann bayer","time":"1:16:14","position":1335,"category_position":null,"gender_position":null},{"name":"suzanne beck","time":"1:16:14","position":1336,"category_position":null,"gender_position":null},{"name":"shane kiernan","time":"1:17:02","position":1360,"category_position":null,"gender_position":null},{"name":"tracey lykiardopulos","time":"1:18:14","position":1378,"category_position":null,"gender_position":null},{"name":"zola dlodlo","time":"1:18:34","position":1387,"category_position":null,"gender_position":null},{"name":"charmaine swain","time":"1:18:43","position":1390,"category_position":null,"gender_position":null},{"name":"nemugumoni livhuwani","time":"1:19:12","position":1408,"category_position":null,"gender_position":null},{"name":"lindsay dawes","time":"1:22:10","position":1452,"category_position":null,"gender_position":null},{"name":"lunga mkosi","time":"1:23:44","position":1478,"category_position":null,"gender_position":null}]},{"fields":{"slug":"century_city_express_2019-03-02_10_run"},"name":"Century City Express","distance":10,"date":"2019-03-02","results":[{"name":"nicholas lykiardopulos","time":"00:39:34","position":50,"category_position":31,"gender_position":45},{"name":"damian will","time":"00:40:00","position":58,"category_position":36,"gender_position":52},{"name":"jonas gensicke","time":"00:40:00","position":59,"category_position":37,"gender_position":53},{"name":"douglas mitchell","time":"00:45:30","position":163,"category_position":12,"gender_position":141},{"name":"andreas gensicke","time":"00:45:36","position":167,"category_position":13,"gender_position":145},{"name":"cavin mcpherson","time":"00:45:39","position":169,"category_position":96,"gender_position":147},{"name":"nancy will","time":"00:46:52","position":207,"category_position":1,"gender_position":28},{"name":"david isaacs","time":"00:47:19","position":233,"category_position":38,"gender_position":201},{"name":"ryan adams","time":"00:47:41","position":245,"category_position":138,"gender_position":211},{"name":"kanakana mushanganyisi","time":"00:49:02","position":309,"category_position":51,"gender_position":262},{"name":"james fish","time":"00:49:22","position":328,"category_position":56,"gender_position":277},{"name":"vera adams","time":"00:50:31","position":396,"category_position":18,"gender_position":59},{"name":"tlou masehela","time":"00:52:36","position":501,"category_position":254,"gender_position":415},{"name":"lily joan","time":"00:52:36","position":502,"category_position":25,"gender_position":87},{"name":"julian smith","time":"00:55:12","position":685,"category_position":317,"gender_position":540},{"name":"jacques verster","time":"00:55:18","position":693,"category_position":51,"gender_position":547},{"name":"mathilda guler","time":"00:56:00","position":754,"category_position":104,"gender_position":173},{"name":"shamiel mathews","time":"00:56:24","position":782,"category_position":56,"gender_position":600},{"name":"peter anders","time":"00:56:25","position":783,"category_position":57,"gender_position":601},{"name":"lyndon young","time":"00:57:15","position":845,"category_position":367,"gender_position":635},{"name":"byron coe","time":"00:58:52","position":978,"category_position":418,"gender_position":715},{"name":"paul meeser","time":"00:59:07","position":1016,"category_position":434,"gender_position":739},{"name":"tegan rowe","time":"00:59:09","position":1022,"category_position":167,"gender_position":279},{"name":"marlene james","time":"00:59:41","position":1083,"category_position":3,"gender_position":306},{"name":"astrid ruiters","time":"01:01:06","position":1175,"category_position":89,"gender_position":347},{"name":"michael roman","time":"01:01:21","position":1194,"category_position":483,"gender_position":833},{"name":"miche africa","time":"01:02:01","position":1256,"category_position":238,"gender_position":392},{"name":"marilyn rorich","time":"01:02:04","position":1260,"category_position":44,"gender_position":393},{"name":"brian samuels","time":"01:03:18","position":1376,"category_position":89,"gender_position":919},{"name":"edgar rorich","time":"01:04:32","position":1487,"category_position":100,"gender_position":968},{"name":"taryn leendertz","time":"01:04:58","position":1514,"category_position":318,"gender_position":537},{"name":"renda tshifularo","time":"01:05:12","position":1531,"category_position":568,"gender_position":985},{"name":"andrew trench","time":"01:05:32","position":1558,"category_position":231,"gender_position":993},{"name":"sean harris","time":"01:05:39","position":1567,"category_position":108,"gender_position":997},{"name":"liesl winter","time":"01:05:40","position":1568,"category_position":338,"gender_position":571},{"name":"wendal smith","time":"01:05:40","position":1569,"category_position":109,"gender_position":998},{"name":"phillipa cloete","time":"01:05:42","position":1572,"category_position":66,"gender_position":573},{"name":"joan bull","time":"01:06:32","position":1627,"category_position":159,"gender_position":606},{"name":"joy cupido","time":"01:06:32","position":1628,"category_position":160,"gender_position":607},{"name":"nicole brooks","time":"01:07:02","position":1670,"category_position":165,"gender_position":637},{"name":"meghann bayer","time":"01:07:11","position":1687,"category_position":384,"gender_position":648},{"name":"roy macgregor","time":"01:07:24","position":1712,"category_position":47,"gender_position":1052},{"name":"unathi solora","time":"01:08:20","position":1782,"category_position":615,"gender_position":1077},{"name":"insula solomons","time":"01:08:41","position":1806,"category_position":422,"gender_position":721},{"name":"aletta basson","time":"01:08:41","position":1807,"category_position":87,"gender_position":722},{"name":"katharina gensicke","time":"01:08:42","position":1810,"category_position":423,"gender_position":724},{"name":"linda zenzile","time":"01:09:18","position":1870,"category_position":197,"gender_position":769},{"name":"yusuf ","time":"01:10:08","position":1972,"category_position":130,"gender_position":1133},{"name":"renata gensicke","time":"01:10:16","position":2005,"category_position":216,"gender_position":864},{"name":"jennifer white","time":"01:11:10","position":2071,"category_position":229,"gender_position":907},{"name":"jennifer samsodien","time":"01:11:31","position":2089,"category_position":234,"gender_position":921},{"name":"patricia swart","time":"01:11:34","position":2095,"category_position":550,"gender_position":924},{"name":"peter arendse","time":"01:11:59","position":2117,"category_position":136,"gender_position":1177},{"name":"linda mallon","time":"01:11:59","position":2118,"category_position":114,"gender_position":941},{"name":"susan merven","time":"01:12:52","position":2174,"category_position":252,"gender_position":983},{"name":"jayne roestorf","time":"01:13:00","position":2184,"category_position":254,"gender_position":990},{"name":"shante phillips","time":"01:14:12","position":2296,"category_position":623,"gender_position":1064},{"name":"brian white","time":"01:14:54","position":2346,"category_position":147,"gender_position":1245},{"name":"hajiera jinoo","time":"01:15:27","position":2380,"category_position":287,"gender_position":1125},{"name":"ren??e fourie","time":"01:16:36","position":2448,"category_position":34,"gender_position":1173},{"name":"livhuwani nemugumoni","time":"01:16:47","position":2470,"category_position":717,"gender_position":1284},{"name":"belinda rhodes","time":"01:16:54","position":2480,"category_position":302,"gender_position":1194},{"name":"lee-ann harris","time":"01:16:54","position":2482,"category_position":138,"gender_position":1196},{"name":"brent van","time":"01:17:17","position":2517,"category_position":307,"gender_position":1223},{"name":"lusanda ngxonono","time":"01:19:34","position":2630,"category_position":325,"gender_position":1306},{"name":"zola dlodlo","time":"01:19:45","position":2639,"category_position":771,"gender_position":1313},{"name":"shane kiernan","time":"01:20:21","position":2686,"category_position":163,"gender_position":1338},{"name":"nomonde kubheka","time":"01:21:38","position":2751,"category_position":349,"gender_position":1395},{"name":"angelo marais","time":"01:22:19","position":2792,"category_position":314,"gender_position":1367},{"name":"tracy marais","time":"01:22:21","position":2794,"category_position":820,"gender_position":1427},{"name":"charmaine swain","time":"01:22:42","position":2806,"category_position":176,"gender_position":1435},{"name":"ailsa dalton","time":"01:23:44","position":2854,"category_position":46,"gender_position":1473},{"name":"keith dalton","time":"01:23:50","position":2857,"category_position":74,"gender_position":1382},{"name":"sarah buchner","time":"01:24:40","position":2895,"category_position":190,"gender_position":1512},{"name":"tania blauw","time":"01:25:00","position":2915,"category_position":380,"gender_position":1527},{"name":"michael haw","time":"01:25:04","position":2919,"category_position":75,"gender_position":1389},{"name":"cathy austin","time":"01:25:11","position":2921,"category_position":382,"gender_position":1532},{"name":"likho sikutshwa","time":"01:26:23","position":2961,"category_position":901,"gender_position":1564},{"name":"chantal rhode","time":"01:26:36","position":2968,"category_position":904,"gender_position":1571},{"name":"abby t","time":"01:26:36","position":2969,"category_position":389,"gender_position":1572},{"name":"lunga mkosi","time":"01:26:43","position":2974,"category_position":907,"gender_position":1577},{"name":"kariema simons","time":"01:29:44","position":3054,"category_position":56,"gender_position":1635},{"name":"paul rist","time":"01:30:05","position":3061,"category_position":171,"gender_position":1420},{"name":"nadeema marks","time":"01:32:07","position":3102,"category_position":213,"gender_position":1671},{"name":"pamela patricia","time":"01:33:28","position":3129,"category_position":414,"gender_position":1694},{"name":"akhona lungsile","time":"01:34:01","position":3135,"category_position":782,"gender_position":1437},{"name":"anastacia james","time":"01:34:55","position":3150,"category_position":968,"gender_position":1709},{"name":"mercia smith","time":"01:35:00","position":3151,"category_position":218,"gender_position":1710},{"name":"nina grobler","time":"01:43:10","position":3249,"category_position":997,"gender_position":1792},{"name":"shavina naidoo","time":"01:46:35","position":3278,"category_position":1010,"gender_position":1816},{"name":"veena naran-smith","time":"01:46:36","position":3279,"category_position":1011,"gender_position":1817}]}]}},"pageContext":{"isCreatedByStatefulCreatePages":false,"name":"shane kiernan"}}